claude_switch/__init__.py
claude_switch/cli.py
claude_switch/config.py
claude_switch/core.py
claude_switch/env-deploy.sh
claude_switch-1.3.1.dist-info/METADATA
claude_switch-1.3.1.dist-info/WHEEL
claude_switch-1.3.1.dist-info/entry_points.txt
claude_switch-1.3.1.dist-info/licenses/LICENSE
claude_switch-1.3.1.dist-info/RECORD
