Metadata-Version: 2.4
Name: claude-switch
Version: 1.3.1
Summary: Anthropic Claude API 配置管理工具，支持多环境切换
Project-URL: Homepage, https://github.com/elicc/claude-switch
Project-URL: Repository, https://github.com/elicc/claude-switch
Project-URL: Documentation, https://github.com/elicc/claude-switch#readme
Project-URL: Issues, https://github.com/elicc/claude-switch/issues
Project-URL: Changelog, https://github.com/elicc/claude-switch/releases
Author-email: Claude <noreply@anthropic.com>
License: MIT
License-File: LICENSE
Keywords: anthropic,api,claude,cli,config,environment,switch
Classifier: Development Status :: 4 - Beta
Classifier: Environment :: Console
Classifier: Intended Audience :: Developers
Classifier: License :: OSI Approved :: MIT License
Classifier: Operating System :: MacOS
Classifier: Operating System :: Microsoft :: Windows
Classifier: Operating System :: POSIX :: Linux
Classifier: Programming Language :: Python :: 3
Classifier: Programming Language :: Python :: 3.8
Classifier: Programming Language :: Python :: 3.9
Classifier: Programming Language :: Python :: 3.10
Classifier: Programming Language :: Python :: 3.11
Classifier: Programming Language :: Python :: 3.12
Classifier: Topic :: Software Development :: Libraries :: Python Modules
Classifier: Topic :: System :: Systems Administration
Classifier: Topic :: Utilities
Requires-Python: >=3.8
Requires-Dist: click>=8.0.0
Requires-Dist: json-repair>=0.30.0
Requires-Dist: questionary>=2.0.0
